polls/__init__.py
polls/admin.py
polls/apps.py
polls/models.py
polls/tests.py
polls/urls.py
polls/views.py
polls/migrations/0001_initial.py
polls/migrations/__init__.py
debshreya-0.0.1.dist-info/LICENSE
debshreya-0.0.1.dist-info/METADATA
debshreya-0.0.1.dist-info/WHEEL
debshreya-0.0.1.dist-info/top_level.txt
debshreya-0.0.1.dist-info/RECORD
