Metadata-Version: 2.1
Name: debshreya
Version: 0.0.1
Summary: A small example package
Home-page: https://www.example.com/
Author: Your Name
Author-email: Shreya <shreya.deb@icloud.com>
License: BSD-3-Clause  # Example license
Project-URL: Homepage, https://github.com/pypa/sampleproject
Project-URL: Bug Tracker, https://github.com/pypa/sampleproject/issues
Classifier: Programming Language :: Python :: 3
Classifier: License :: OSI Approved :: MIT License
Classifier: Operating System :: OS Independent
Requires-Python: >=3.7
License-File: LICENSE
Requires-Dist: Django >=2.2
